README.md
setup.py
cursotools/__init__.py
cursotools/github_api.py
cursotools.egg-info/PKG-INFO
cursotools.egg-info/SOURCES.txt
cursotools.egg-info/dependency_links.txt
cursotools.egg-info/not-zip-safe
cursotools.egg-info/requires.txt
cursotools.egg-info/top_level.txt
libpythonpro/__init__.py
libpythonpro/github_api.py